{".class":"MypyFile","_fullname":"requests_cache.backends.gridfs","future_import_flags":[],"is_partial_stub_package":false,"is_stub":false,"names":{".class":"SymbolTable","BaseCache":{".class":"SymbolTableNode","cross_ref":"requests_cache.backends.base.BaseCache","kind":"Gdef"},"BaseStorage":{".class":"SymbolTableNode","cross_ref":"requests_cache.backends.base.BaseStorage","kind":"Gdef"},"CorruptGridFile":{".class":"SymbolTableNode","kind":"Gdef","node":{".class":"Var","flags":["is_suppressed_import","is_ready","is_inferred"],"fullname":"requests_cache.backends.gridfs.CorruptGridFile","name":"CorruptGridFile","setter_type":null,"type":{".class":"AnyType","missing_import_name":"requests_cache.backends.gridfs.CorruptGridFile","source_any":null,"type_of_any":3}}},"FileExists":{".class":"SymbolTableNode","kind":"Gdef","node":{".class":"Var","flags":["is_suppressed_import","is_ready","is_inferred"],"fullname":"requests_cache.backends.gridfs.FileExists","name":"FileExists","setter_type":null,"type":{".class":"AnyType","missing_import_name":"requests_cache.backends.gridfs.FileExists","source_any":null,"type_of_any":3}}},"GridFS":{".class":"SymbolTableNode","kind":"Gdef","node":{".class":"Var","flags":["is_suppressed_import","is_ready","is_inferred"],"fullname":"requests_cache.backends.gridfs.GridFS","name":"GridFS","setter_type":null,"type":{".class":"AnyType","missing_import_name":"requests_cache.backends.gridfs.GridFS","source_any":null,"type_of_any":3}}},"GridFSCache":{".class":"SymbolTableNode","kind":"Gdef","node":{".class":"TypeInfo","_promote":[],"abstract_attributes":[],"alt_promote":null,"bases":["requests_cache.backends.base.BaseCache"],"dataclass_transform_spec":null,"declared_metaclass":null,"defn":{".class":"ClassDef","fullname":"requests_cache.backends.gridfs.GridFSCache","name":"GridFSCache","type_vars":[]},"deletable_attributes":[],"deprecated":null,"flags":[],"fullname":"requests_cache.backends.gridfs.GridFSCache","has_param_spec_type":false,"metaclass_type":null,"metadata":{},"module_name":"requests_cache.backends.gridfs","mro":["requests_cache.backends.gridfs.GridFSCache","requests_cache.backends.base.BaseCache","builtins.object"],"names":{".class":"SymbolTable","__init__":{".class":"SymbolTableNode","kind":"Mdef","node":{".class":"FuncDef","abstract_status":0,"arg_kinds":[0,0,1,1,4],"arg_names":["self","db_name","decode_content","serializer","kwargs"],"dataclass_transform_spec":null,"deprecated":null,"flags":["is_trivial_self"],"fullname":"requests_cache.backends.gridfs.GridFSCache.__init__","name":"__init__","original_first_arg":"self","type":{".class":"CallableType","arg_kinds":[0,0,1,1,4],"arg_names":["self","db_name","decode_content","serializer","kwargs"],"arg_types":["requests_cache.backends.gridfs.GridFSCache","builtins.str","builtins.bool",{".class":"UnionType","items":[{".class":"TypeAliasType","args":[],"type_ref":"requests_cache.serializers.SerializerType"},{".class":"NoneType"}],"uses_pep604_syntax":false},{".class":"AnyType","missing_import_name":null,"source_any":null,"type_of_any":1}],"fallback":"builtins.function","from_concatenate":false,"implicit":false,"imprecise_arg_kinds":false,"is_bound":false,"is_ellipsis_args":false,"name":"__init__ of GridFSCache","ret_type":{".class":"NoneType"},"type_guard":null,"type_is":null,"unpack_kwargs":false,"variables":[]}}},"delete":{".class":"SymbolTableNode","kind":"Mdef","node":{".class":"FuncDef","abstract_status":0,"arg_kinds":[0,2,4],"arg_names":["self","args","kwargs"],"dataclass_transform_spec":null,"deprecated":null,"flags":[],"fullname":"requests_cache.backends.gridfs.GridFSCache.delete","name":"delete","original_first_arg":"self","type":null}}},"self_type":{".class":"TypeVarType","default":{".class":"AnyType","missing_import_name":null,"source_any":null,"type_of_any":4},"fullname":"requests_cache.backends.gridfs.GridFSCache.Self","id":0,"name":"Self","namespace":"","upper_bound":"requests_cache.backends.gridfs.GridFSCache","values":[],"variance":0},"slots":null,"tuple_type":null,"type_vars":[],"typeddict_type":null}},"GridFSDict":{".class":"SymbolTableNode","kind":"Gdef","node":{".class":"TypeInfo","_promote":[],"abstract_attributes":[],"alt_promote":null,"bases":[{".class":"Instance","args":[{".class":"AnyType","missing_import_name":null,"source_any":null,"type_of_any":4},{".class":"AnyType","missing_import_name":null,"source_any":null,"type_of_any":4}],"extra_attrs":null,"type_ref":"requests_cache.backends.base.BaseStorage"}],"dataclass_transform_spec":null,"declared_metaclass":null,"defn":{".class":"ClassDef","fullname":"requests_cache.backends.gridfs.GridFSDict","name":"GridFSDict","type_vars":[]},"deletable_attributes":[],"deprecated":null,"flags":[],"fullname":"requests_cache.backends.gridfs.GridFSDict","has_param_spec_type":false,"metaclass_type":"abc.ABCMeta","metadata":{},"module_name":"requests_cache.backends.gridfs","mro":["requests_cache.backends.gridfs.GridFSDict","requests_cache.backends.base.BaseStorage","typing.MutableMapping","typing.Mapping","typing.Collection","typing.Iterable","typing.Container","abc.ABC","builtins.object"],"names":{".class":"SymbolTable","__delitem__":{".class":"SymbolTableNode","kind":"Mdef","node":{".class":"FuncDef","abstract_status":0,"arg_kinds":[0,0],"arg_names":[null,null],"dataclass_transform_spec":null,"deprecated":null,"flags":[],"fullname":"requests_cache.backends.gridfs.GridFSDict.__delitem__","name":"__delitem__","original_first_arg":"self","type":null}},"__getitem__":{".class":"SymbolTableNode","kind":"Mdef","node":{".class":"FuncDef","abstract_status":0,"arg_kinds":[0,0],"arg_names":[null,null],"dataclass_transform_spec":null,"deprecated":null,"flags":[],"fullname":"requests_cache.backends.gridfs.GridFSDict.__getitem__","name":"__getitem__","original_first_arg":"self","type":null}},"__init__":{".class":"SymbolTableNode","kind":"Mdef","node":{".class":"FuncDef","abstract_status":0,"arg_kinds":[0,0,1,1,1,4],"arg_names":["self","db_name","collection_name","connection","serializer","kwargs"],"dataclass_transform_spec":null,"deprecated":null,"flags":["is_trivial_self"],"fullname":"requests_cache.backends.gridfs.GridFSDict.__init__","name":"__init__","original_first_arg":"self","type":{".class":"CallableType","arg_kinds":[0,0,1,1,1,4],"arg_names":["self","db_name","collection_name","connection","serializer","kwargs"],"arg_types":["requests_cache.backends.gridfs.GridFSDict",{".class":"AnyType","missing_import_name":null,"source_any":null,"type_of_any":1},{".class":"AnyType","missing_import_name":null,"source_any":null,"type_of_any":1},{".class":"AnyType","missing_import_name":null,"source_any":null,"type_of_any":1},{".class":"UnionType","items":[{".class":"TypeAliasType","args":[],"type_ref":"requests_cache.serializers.SerializerType"},{".class":"NoneType"}],"uses_pep604_syntax":false},{".class":"AnyType","missing_import_name":null,"source_any":null,"type_of_any":1}],"fallback":"builtins.function","from_concatenate":false,"implicit":false,"imprecise_arg_kinds":false,"is_bound":false,"is_ellipsis_args":false,"name":"__init__ of GridFSDict","ret_type":{".class":"NoneType"},"type_guard":null,"type_is":null,"unpack_kwargs":false,"variables":[]}}},"__iter__":{".class":"SymbolTableNode","kind":"Mdef","node":{".class":"FuncDef","abstract_status":0,"arg_kinds":[0],"arg_names":[null],"dataclass_transform_spec":null,"deprecated":null,"flags":[],"fullname":"requests_cache.backends.gridfs.GridFSDict.__iter__","name":"__iter__","original_first_arg":"self","type":null}},"__len__":{".class":"SymbolTableNode","kind":"Mdef","node":{".class":"FuncDef","abstract_status":0,"arg_kinds":[0],"arg_names":[null],"dataclass_transform_spec":null,"deprecated":null,"flags":[],"fullname":"requests_cache.backends.gridfs.GridFSDict.__len__","name":"__len__","original_first_arg":"self","type":null}},"__setitem__":{".class":"SymbolTableNode","kind":"Mdef","node":{".class":"FuncDef","abstract_status":0,"arg_kinds":[0,0,0],"arg_names":[null,null,null],"dataclass_transform_spec":null,"deprecated":null,"flags":[],"fullname":"requests_cache.backends.gridfs.GridFSDict.__setitem__","name":"__setitem__","original_first_arg":"self","type":null}},"_lock":{".class":"SymbolTableNode","implicit":true,"kind":"Mdef","node":{".class":"Var","flags":["is_ready","is_inferred"],"fullname":"requests_cache.backends.gridfs.GridFSDict._lock","name":"_lock","setter_type":null,"type":"_thread.RLock"}},"clear":{".class":"SymbolTableNode","kind":"Mdef","node":{".class":"FuncDef","abstract_status":0,"arg_kinds":[0],"arg_names":["self"],"dataclass_transform_spec":null,"deprecated":null,"flags":[],"fullname":"requests_cache.backends.gridfs.GridFSDict.clear","name":"clear","original_first_arg":"self","type":null}},"connection":{".class":"SymbolTableNode","implicit":true,"kind":"Mdef","node":{".class":"Var","flags":["is_ready","is_inferred"],"fullname":"requests_cache.backends.gridfs.GridFSDict.connection","name":"connection","setter_type":null,"type":{".class":"AnyType","missing_import_name":null,"source_any":null,"type_of_any":1}}},"db":{".class":"SymbolTableNode","implicit":true,"kind":"Mdef","node":{".class":"Var","flags":["is_ready","is_inferred"],"fullname":"requests_cache.backends.gridfs.GridFSDict.db","name":"db","setter_type":null,"type":{".class":"AnyType","missing_import_name":null,"source_any":{".class":"AnyType","missing_import_name":null,"source_any":null,"type_of_any":1},"type_of_any":7}}},"fs":{".class":"SymbolTableNode","implicit":true,"kind":"Mdef","node":{".class":"Var","flags":["is_ready","is_inferred"],"fullname":"requests_cache.backends.gridfs.GridFSDict.fs","name":"fs","setter_type":null,"type":{".class":"AnyType","missing_import_name":"requests_cache.backends.gridfs.GridFS","source_any":{".class":"AnyType","missing_import_name":"requests_cache.backends.gridfs.GridFS","source_any":null,"type_of_any":3},"type_of_any":7}}}},"self_type":{".class":"TypeVarType","default":{".class":"AnyType","missing_import_name":null,"source_any":null,"type_of_any":4},"fullname":"requests_cache.backends.gridfs.GridFSDict.Self","id":0,"name":"Self","namespace":"","upper_bound":"requests_cache.backends.gridfs.GridFSDict","values":[],"variance":0},"slots":null,"tuple_type":null,"type_vars":[],"typeddict_type":null}},"MongoClient":{".class":"SymbolTableNode","kind":"Gdef","node":{".class":"Var","flags":["is_suppressed_import","is_ready","is_inferred"],"fullname":"requests_cache.backends.gridfs.MongoClient","name":"MongoClient","setter_type":null,"type":{".class":"AnyType","missing_import_name":"requests_cache.backends.gridfs.MongoClient","source_any":null,"type_of_any":3}}},"MongoDict":{".class":"SymbolTableNode","cross_ref":"requests_cache.backends.mongodb.MongoDict","kind":"Gdef"},"Optional":{".class":"SymbolTableNode","cross_ref":"typing.Optional","kind":"Gdef"},"RLock":{".class":"SymbolTableNode","cross_ref":"threading.RLock","kind":"Gdef"},"SerializerType":{".class":"SymbolTableNode","cross_ref":"requests_cache.serializers.SerializerType","kind":"Gdef"},"__annotations__":{".class":"SymbolTableNode","kind":"Gdef","node":{".class":"Var","flags":["is_ready"],"fullname":"requests_cache.backends.gridfs.__annotations__","name":"__annotations__","setter_type":null,"type":{".class":"Instance","args":["builtins.str",{".class":"AnyType","missing_import_name":null,"source_any":null,"type_of_any":6}],"extra_attrs":null,"type_ref":"builtins.dict"}}},"__doc__":{".class":"SymbolTableNode","kind":"Gdef","node":{".class":"Var","flags":["is_ready"],"fullname":"requests_cache.backends.gridfs.__doc__","name":"__doc__","setter_type":null,"type":"builtins.str"}},"__file__":{".class":"SymbolTableNode","kind":"Gdef","node":{".class":"Var","flags":["is_ready"],"fullname":"requests_cache.backends.gridfs.__file__","name":"__file__","setter_type":null,"type":"builtins.str"}},"__name__":{".class":"SymbolTableNode","kind":"Gdef","node":{".class":"Var","flags":["is_ready"],"fullname":"requests_cache.backends.gridfs.__name__","name":"__name__","setter_type":null,"type":"builtins.str"}},"__package__":{".class":"SymbolTableNode","kind":"Gdef","node":{".class":"Var","flags":["is_ready"],"fullname":"requests_cache.backends.gridfs.__package__","name":"__package__","setter_type":null,"type":"builtins.str"}},"__spec__":{".class":"SymbolTableNode","kind":"Gdef","node":{".class":"Var","flags":["is_ready"],"fullname":"requests_cache.backends.gridfs.__spec__","name":"__spec__","setter_type":null,"type":"_frozen_importlib.ModuleSpec"}},"getLogger":{".class":"SymbolTableNode","cross_ref":"logging.getLogger","kind":"Gdef"},"get_valid_kwargs":{".class":"SymbolTableNode","cross_ref":"requests_cache._utils.get_valid_kwargs","kind":"Gdef"},"logger":{".class":"SymbolTableNode","kind":"Gdef","node":{".class":"Var","flags":["is_ready","is_inferred","has_explicit_value"],"fullname":"requests_cache.backends.gridfs.logger","name":"logger","setter_type":null,"type":"logging.Logger"}},"pickle_serializer":{".class":"SymbolTableNode","cross_ref":"requests_cache.serializers.preconf.pickle_serializer","kind":"Gdef"}},"path":"C:\\Users\\Stelios\\AppData\\Roaming\\Python\\Python313\\site-packages\\requests_cache\\backends\\gridfs.py"}